{
  "cloudflare_worker_url": "https://nano-sender.yourdomain.workers.dev/sendNano",
  "cloudflare_api_key": "",
  "solana_rpc_url": "https://api.mainnet-beta.solana.com",
  "jupiter_quote_api": "https://quote-api.jup.ag/v6/quote",
  "jupiter_swap_api": "https://quote-api.jup.ag/v6/swap",
  "usdc_min_amount": 0.01,
  "usdc_max_amount": 1000.0,
  "ar_min_amount": 0.001,
  "ar_max_amount": 100.0,
  "arweave_native_provider": "everpay",
  "everpay_api_url": "https://api.everpay.io",
  "everpay_input_token": "ethereum-usdc-0xa0b86991c6218b36c1d19d4a2e9eb0ce3606eb48",
  "everpay_ar_token": "arweave,ethereum-ar-AAAAAAAAAAAAAAAAAAAAAAAAAAAAAAAAAAAAAAAAAAA,0x4fadc7a98f2dc96510e42dd1a74141eeae0c1543",
  "everpay_address": "",
  "nano_min_amount": 0.001,
  "nano_max_amount": 1.0,
  "nano_rpc_url": "https://mynano.ninja/api",
  "request_timeout": 30,
  "health_check_timeout": 10,
  "max_retries": 3,
  "retry_delay": 2,
  "enable_cloudflare_nano": true,
  "enable_arweave_purchase": true,
  "enable_balance_check": true
}